pseudopatch/__init__.py
pseudopatch/api.py
pseudopatch/cli.py
pseudopatch/domain.py
pseudopatch/exceptions.py
pseudopatch/patching.py
pseudopatch-0.1.0.dist-info/licenses/LICENSE
pseudopatch-0.1.0.dist-info/METADATA
pseudopatch-0.1.0.dist-info/WHEEL
pseudopatch-0.1.0.dist-info/entry_points.txt
pseudopatch-0.1.0.dist-info/top_level.txt
pseudopatch-0.1.0.dist-info/RECORD
