Metadata-Version: 2.4
Name: pseudopatch
Version: 0.1.0
Summary: A utility for applying human-readable pseudo-diff patch files.
Author-email: Shang En Sim <sim@shangen.org>
Classifier: Programming Language :: Python :: 3
Classifier: License :: OSI Approved :: MIT License
Classifier: Operating System :: OS Independent
Requires-Python: >=3.9
License-File: LICENSE
Dynamic: license-file
